nikw/main.py
nikw/main.py~
nikw-0.0.0.dist-info/LICENSE
nikw-0.0.0.dist-info/WHEEL
nikw-0.0.0.dist-info/METADATA
nikw-0.0.0.dist-info/RECORD
