Metadata-Version: 2.1
Name: nikw
Version: 0.0.0
Summary: Nikw, a game solver.
License: GPLv3
Author: suizokukan
Author-email: suizokukan@orange.fr
Requires-Python: >=3.9,<4.0
Classifier: License :: Other/Proprietary License
Classifier: Programming Language :: Python :: 3
Classifier: Programming Language :: Python :: 3.9
Requires-Dist: pytest (>=6.1.2,<7.0.0)
